loggerjava/__init__.py
loggerjava/exceptionhandler.py
loggerjava/loggerjava.py
loggerjava/test_loggerjava.py
loggerjava-0.8.0.dist-info/LICENSE
loggerjava-0.8.0.dist-info/METADATA
loggerjava-0.8.0.dist-info/WHEEL
loggerjava-0.8.0.dist-info/top_level.txt
loggerjava-0.8.0.dist-info/RECORD
