Metadata-Version: 2.1
Name: loggerjava
Version: 0.8.0
Summary: an easy logger outputs like java logs
Author: HTony03
Author-email: HTony03 <HTony03@foxmail.com>
Project-URL: Homepage, https://github.com/HTony03/loggerjava
Project-URL: Issues, https://github.com/HTony03/loggerjava/issues
Keywords: python,logger,java_like
Classifier: Programming Language :: Python :: 3
Classifier: License :: OSI Approved :: MIT License
Classifier: Operating System :: OS Independent
Requires-Python: >=3.8
License-File: LICENSE
